otter/__init__.py
otter/__main__.py
otter/definitions.py
otter/styling.py
otter/types.py
otter/core/__init__.py
otter/core/chunks.py
otter/core/events.py
otter/core/tasks.py
otter/log/__init__.py
otter/log/config/__init__.py
otter/log/config/standard.yaml
otter/reporting/__init__.py
otter/reporting/classes.py
otter/reporting/make.py
otter/reporting/report.py
otter/reporting/utils.py
otter/reporting/templates/__init__.py
otter/utils/__init__.py
otter/utils/counters.py
otter/utils/edge_predicates.py
otter/utils/iterate.py
otter/utils/vertex_attr_handlers.py
otter/utils/vertex_predicates.py
pyotter-0.2.0.dist-info/LICENSE
pyotter-0.2.0.dist-info/METADATA
pyotter-0.2.0.dist-info/WHEEL
pyotter-0.2.0.dist-info/dependency_links.txt
pyotter-0.2.0.dist-info/top_level.txt
pyotter-0.2.0.dist-info/RECORD
