Metadata-Version: 2.1
Name: pyotter
Version: 0.2.0
Summary: Otter post-processing tool
Home-page: https://github.com/Otter-Taskification/pyotter
Author: Adam Tuft
Author-email: adam.s.tuft@durham.ac.uk
License: https://github.com/Otter-Taskification/pyotter/blob/dev/LICENSE
Platform: linux
License-File: LICENSE
Requires-Dist: pyyaml (>=6.0)
Requires-Dist: python-igraph (==0.9.1)
Requires-Dist: loggingdecorators (>=0.1.3)
